luxwidget/__init__.py
luxwidget/_frontend.py
luxwidget/_version.py
luxwidget/widget.py
luxwidget/nbextension/__init__.py
luxwidget/nbextension/static/extension.js
luxwidget/nbextension/static/index.js
luxwidget/nbextension/static/index.js.map
lux_widget-0.1.0.dist-info/LICENSE
lux_widget-0.1.0.dist-info/METADATA
lux_widget-0.1.0.dist-info/WHEEL
lux_widget-0.1.0.dist-info/top_level.txt
lux_widget-0.1.0.dist-info/RECORD
