Metadata-Version: 2.1
Name: lux-widget
Version: 0.1.0
Summary: Jupyter Widget for Intelligent Data Discovery
Home-page: https://github.com/lux-org/luxwidget
Author: Doris Jung-Lin Lee
Author-email: dorisjunglinlee@gmail.com
License: Apache-2.0 License
Keywords: Jupyter,Widgets,Visualization,Analytics,Data Science,Data Analysis,IPython
Platform: Linux
Platform: Mac OS X
Platform: Windows
Classifier: Development Status :: 1 - Planning
Classifier: Intended Audience :: Developers
Classifier: Intended Audience :: Science/Research
Classifier: Intended Audience :: Other Audience
Classifier: Topic :: Scientific/Engineering :: Information Analysis
Classifier: Topic :: Scientific/Engineering :: Visualization
Classifier: License :: OSI Approved :: Apache Software License
Classifier: Programming Language :: Python :: 3
Classifier: Framework :: Jupyter
Requires-Dist: notebook (>=4.0.0)
Requires-Dist: ipywidgets (>=7.0.0)
